llmexport/__init__.py
llmexport/gguf2mnn.py
llmexport/llmexport.py
llmexport/version.py
llmexport/utils/__init__.py
llmexport/utils/audio.py
llmexport/utils/awq_quantizer.py
llmexport/utils/custom_op.py
llmexport/utils/eagle.py
llmexport/utils/gptq.py
llmexport/utils/hqq_quantizer.py
llmexport/utils/lora.py
llmexport/utils/mnn_converter.py
llmexport/utils/mnn_utils.py
llmexport/utils/model_mapper.py
llmexport/utils/mtp.py
llmexport/utils/onnx.py
llmexport/utils/onnx_rebuilder.py
llmexport/utils/smooth_quantizer.py
llmexport/utils/spinner.py
llmexport/utils/talker.py
llmexport/utils/token2wav.py
llmexport/utils/torch_utils.py
llmexport/utils/transformers.py
llmexport/utils/vision.py
llmexport-0.0.4.dist-info/licenses/LICENSE
llmexport-0.0.4.dist-info/METADATA
llmexport-0.0.4.dist-info/WHEEL
llmexport-0.0.4.dist-info/entry_points.txt
llmexport-0.0.4.dist-info/top_level.txt
llmexport-0.0.4.dist-info/zip-safe
llmexport-0.0.4.dist-info/RECORD
