Metadata-Version: 2.4
Name: llmexport
Version: 0.0.4
Summary: llmexport: A toolkit to export llm to onnx or mnn.
Home-page: https://github.com/wangzhaode/llm-export
Author: wangzhaode
Author-email: hi@zhaode.wang
License: MIT
Project-URL: Bug Tracker, https://github.com/wangzhaode/llm-export/issues
Classifier: Programming Language :: Python :: 3
Classifier: License :: OSI Approved :: MIT License
Classifier: Intended Audience :: Developers
Classifier: Topic :: Scientific/Engineering :: Artificial Intelligence
Requires-Python: >=3.6
License-File: LICENSE
Requires-Dist: yaspin
Requires-Dist: torch
Requires-Dist: numpy
Requires-Dist: transformers
Requires-Dist: sentencepiece
Requires-Dist: onnx
Requires-Dist: onnxslim
Requires-Dist: onnxruntime
Requires-Dist: MNN
Dynamic: author
Dynamic: author-email
Dynamic: classifier
Dynamic: description
Dynamic: description-content-type
Dynamic: home-page
Dynamic: license
Dynamic: license-file
Dynamic: project-url
Dynamic: requires-dist
Dynamic: requires-python
Dynamic: summary
